MANIFEST.in
README.txt
setup.cfg
setup.py
simplemotds/__init__.py
simplemotds/config.json
simplemotds/simplemotds.py
simplemotds.egg-info/PKG-INFO
simplemotds.egg-info/SOURCES.txt
simplemotds.egg-info/dependency_links.txt
simplemotds.egg-info/top_level.txt
simplemotds/messages/m1.html
simplemotds/messages/m2.html
simplemotds/messages/m3.html