Metadata-Version: 1.1
Name: simplemotds
Version: 0.22
Summary: Configurable package that returns the message of the day (motd)
Home-page: https://github.com/strymsg/python-simplemotds
Author: Rodrigo Garcia
Author-email: strysg@riseup.net
License: GPLv3
Platform: UNKNOWN
Classifier: Programming Language :: Python :: 3
Classifier: License :: OSI Approved :: GNU General Public License v3 (GPLv3)
Classifier: Development Status :: 4 - Beta
Classifier: Intended Audience :: Developers
Classifier: Operating System :: OS Independent
